asn1/__init__.py
asn1/core.py
asn1/core.pyi
asn1/py.typed
asn1-3.1.0.dist-info/licenses/AUTHORS.rst
asn1-3.1.0.dist-info/licenses/LICENSE
asn1-3.1.0.dist-info/METADATA
asn1-3.1.0.dist-info/WHEEL
asn1-3.1.0.dist-info/top_level.txt
asn1-3.1.0.dist-info/RECORD
